device/__init__.py
device/base.py
device/device.py
device/message.py
device/parser.py
network/__init__.py
network/tcp.py
network/udp.py
utils/__init__.py
utils/crcutils.py
utils/local.py
x7base/__init__.py
x7base/devinfo.py
x7base/model.py
x7base/x7parser.py
x7base/x7tcp.py
x7base/x7udp.py
x7base/x7utils.py
qldevice-1.0.0.dist-info/METADATA
qldevice-1.0.0.dist-info/WHEEL
qldevice-1.0.0.dist-info/top_level.txt
qldevice-1.0.0.dist-info/RECORD
