Metadata-Version: 2.1
Name: qldevice
Version: 1.0.0
Summary: api for x7 box since v1.0
Author: eegion
Author-email: hehuajun@eegion.com
